{
    "title" : "Рубленое тесто",
    "src": "https://maria-kitchen.livejournal.com/52870.html",
    "category" : "desserts",
    "tags" : [ 
        "desserts",
        "тесто"
    ],
    "notes" : [
        "На примере абстрактного тарта"
    ],
    "ingredients" : [ 
        {
            "amount" : "250 г",
            "name" : "мука"
        }, 
        {
            "amount" : "100 г",
            "name" : "масло"
        }, 
        {
            "amount" : "щепотка",
            "name" : "соль"
        }, 
        {
            "amount" : "1 шт",
            "name" : "яйцо"
        },
        {
            "amount" : "1 ст.л",
            "name" : "мед"
        }
    ],
    "instructions" : [
        {
            "text": "Муку смешайте с солью, добавьте холодное сливочное масло.",
            "input": [{
                "ingredient": 0
            }, {
                "ingredient": 1
            }, {
                "ingredient": 2
            }],
            "output": [{
                "name": "мучная смесь"
            }],
            "richtext": "<link:input num=0>Муку</link> смешайте с <link:input num=2>солью</link>, добавьте <link:input num=1>холодное сливочное масло</link>."
        },
        {
            "input": [{
                "output": 0
            }],
            "output": [{
                "name": "мучная смесь (рубленая)"
            }],
            "text": "Всю мучную смесь порубите в крошку (удобнее всего делать в блендере или фуд-процессоре).",
            "richtext": "<link:input num=0>Всю мучную смесь</link> порубите в крошку (удобнее всего делать в блендере или фуд-процессоре)."
        },
        {
            "input": [{
                "output": 1
            }, {
                "ingredient": 3
            }],
            "output": [{
                "name": "тесто"
            }],
            "text": "Добавьте яйцо и немного воды, если необходимо. Тесто должно собраться в шар.",
            "richtext": "Добавьте <link:input num=1>яйцо</link> и немного воды, если необходимо. Тесто должно собраться в шар."
        },
        {
            "input": [{
                "output": 2
            }],
            "output": [{
                "name": "тесто (1)"
            }],
            "text": "Заверните его в пленку и уберите в холодильник на час.",
            "richtext": "Заверните <link:input num=0>его</link> в пленку и уберите в холодильник на час."
        },
        {
            "text": "Через час разогрейте духовку до 180 градусов."
        },
        {
            "input": [{
                "output": 3
            }],
            "output": [{
                "name": "форма из теста (полуготовая)"
            }],
            "text": "Раскатайте тесто и поместите его в форму (можно раскатывать сразу после замеса и охлаждать в форме, так даже легче). Наколите тесто вилкой и поставьте на 10 минут в духовку.",
            "richtext": "Раскатайте <link:input num=0>тесто</link> и поместите его в форму (можно раскатывать сразу после замеса и охлаждать в форме, так даже легче). Наколите тесто вилкой и поставьте на 10 минут в духовку.",
            "image": "http://img-fotki.yandex.ru/get/4406/mariha-kitchen.27/0_64b7c_3419aa58_M"
        },
        {
            "input": [{
                "output": 4
            }, {
                "ingredient": 4
            }],
            "output": [{
                "name": "форма из теста (полуготовая) (1)"
            }],
            "text": "В сотейнике разогрейте мед, он должен быть совсем жидким. Достаньте форму с тестом из духовки и кистью смажьте тесто медом.",
            "richtext": "В сотейнике разогрейте <link:input num=1>мед</link>, он должен быть совсем жидким. Достаньте <link:input num=0>форму с тестом</link> из духовки и кистью смажьте тесто медом.",
            "images": [
                "http://img-fotki.yandex.ru/get/5010/mariha-kitchen.27/0_64b7b_d057cd8e_M",
                "http://img-fotki.yandex.ru/get/5806/mariha-kitchen.27/0_64b7d_3cf81a4e_M"
            ]
        },
        {
            "input": [{
                "output": 5
            }],
            "output": [{
                "name": "форма из теста с начинкой"
            }],
            "text": "Выложить начинку"
        },
        {
            "input": [{
                "output": 6
            }],
            "output": [{
                "name": "готовое тесто с начинкой"
            }],
            "text": "Поставьте в духовку и пеките еще минут 25"
        }
    ],
    "cooked" : "true"
}
